sumologic/__init__.py
sumologic/sumologic.py
sumologic_sdk-0.1.17.dist-info/LICENSE
sumologic_sdk-0.1.17.dist-info/METADATA
sumologic_sdk-0.1.17.dist-info/WHEEL
sumologic_sdk-0.1.17.dist-info/top_level.txt
sumologic_sdk-0.1.17.dist-info/zip-safe
sumologic_sdk-0.1.17.dist-info/RECORD
