Metadata-Version: 2.1
Name: sumologic-sdk
Version: 0.1.17
Summary: Sumo Logic Python SDK
Home-page: https://github.com/SumoLogic/sumologic-python-sdk
Author: SumoLogic, Yoway Buorn, Melchi Salins
Author-email: SumoLogic <apps-team@sumologic.com>
License: Apache License
Project-URL: Homepage, https://github.com/SumoLogic/sumologic-python-sdk
Project-URL: Issues, https://github.com/SumoLogic/sumologic-python-sdk/issues
Project-URL: Changelog, https://github.com/SumoLogic/sumologic-python-sdk/blob/master/CHANGELOG.md
Keywords: sumologic,python,sdk,rest,api,log,management,analytics,logreduce,security,siem,collector,forwarder
Classifier: Programming Language :: Python :: 3
Classifier: Programming Language :: Python :: 3.8
Classifier: Programming Language :: Python :: 3.9
Classifier: Programming Language :: Python :: 3.10
Classifier: Programming Language :: Python :: 3.11
Classifier: Programming Language :: Python :: 3.12
Classifier: Operating System :: OS Independent
Requires-Python: >=3.8
License-File: LICENSE
Requires-Dist: requests >=2.32.0
